{
  "insert-template": [
    {
      "modifiers": [
        "Mod",
        "Shift"
      ],
      "key": "K"
    }
  ],
  "workspace:split-vertical": [
    {
      "modifiers": [
        "Alt",
        "Mod"
      ],
      "key": "\\"
    }
  ],
  "workspace:split-horizontal": [
    {
      "modifiers": [
        "Mod",
        "Shift"
      ],
      "key": "\\"
    }
  ],
  "editor:delete-paragraph": [
    {
      "modifiers": [
        "Mod",
        "Shift"
      ],
      "key": "Delete"
    }
  ],
  "global-search:open": [
    {
      "modifiers": [
        "Mod",
        "Shift"
      ],
      "key": "S"
    }
  ],
  "editor:open-search": [],
  "editor:cycle-list-checklist": [
    {
      "modifiers": [
        "Mod",
        "Shift"
      ],
      "key": "L"
    }
  ],
  "editor:swap-line-up": [
    {
      "modifiers": [
        "Alt"
      ],
      "key": "ArrowUp"
    }
  ],
  "editor:swap-line-down": [
    {
      "modifiers": [
        "Alt"
      ],
      "key": "ArrowDown"
    }
  ],
  "editor:attach-file": [
    {
      "modifiers": [
        "Mod",
        "Shift"
      ],
      "key": "I"
    }
  ],
  "window:zoom-in": [
    {
      "modifiers": [
        "Mod"
      ],
      "key": "+"
    }
  ],
  "window:zoom-out": [
    {
      "modifiers": [
        "Mod"
      ],
      "key": "-"
    }
  ],
  "window:reset-zoom": [
    {
      "modifiers": [
        "Mod",
        "Shift"
      ],
      "key": "B"
    }
  ],
  "obsidian-excalidraw-plugin:insert-link": [],
  "editor:save-file": [],
  "obsidian-excalidraw-plugin:insert-link-to-element": [],
  "app:go-back": [
    {
      "modifiers": [
        "Mod",
        "Alt"
      ],
      "key": "ArrowLeft"
    },
    {
      "modifiers": [
        "Mod"
      ],
      "key": "ArrowLeft"
    }
  ],
  "app:go-forward": [
    {
      "modifiers": [
        "Mod",
        "Alt"
      ],
      "key": "ArrowRight"
    },
    {
      "modifiers": [
        "Mod"
      ],
      "key": "ArrowRight"
    }
  ],
  "daily-notes": [
    {
      "modifiers": [
        "Mod"
      ],
      "key": "R"
    }
  ],
  "command-palette:open": [
    {
      "modifiers": [
        "Mod",
        "Shift"
      ],
      "key": "P"
    }
  ],
  "obsidian-projects:show-projects": [
    {
      "modifiers": [
        "Mod"
      ],
      "key": "P"
    }
  ],
  "obsidian-memos:open-memos": [
    {
      "modifiers": [
        "Mod"
      ],
      "key": "M"
    }
  ],
  "obsidian-memos:note-it": [
    {
      "modifiers": [
        "Mod",
        "Shift"
      ],
      "key": "M"
    }
  ],
  "obsidian-memos:show-daily-memo": [],
  "canvas:new-file": [
    {
      "modifiers": [
        "Mod",
        "Shift"
      ],
      "key": "C"
    }
  ],
  "app:toggle-left-sidebar": [
    {
      "modifiers": [
        "Mod"
      ],
      "key": "F"
    }
  ],
  "obsidian-memos:show-thino-in-popover": [],
  "obsidian-memos:open-thino-in-right-sidebar": [
    {
      "modifiers": [
        "Mod"
      ],
      "key": "M"
    }
  ],
  "outline:open": [
    {
      "modifiers": [
        "Mod"
      ],
      "key": "D"
    }
  ],
  "app:toggle-right-sidebar": [
    {
      "modifiers": [
        "Alt",
        "Mod"
      ],
      "key": "F"
    }
  ],
  "markdown:add-metadata-property": [
    {
      "modifiers": [
        "Mod"
      ],
      "key": ";"
    },
    {
      "modifiers": [
        "Alt"
      ],
      "key": "P"
    }
  ],
  "properties:open-local": [
    {
      "modifiers": [
        "Alt",
        "Mod"
      ],
      "key": "P"
    }
  ],
  "file-explorer:reveal-active-file": [
    {
      "modifiers": [
        "Mod",
        "Shift"
      ],
      "key": "F"
    }
  ],
  "notion-like-tables:add-column": []
}